{
  "project_info": {
    "project_number": "141070416734",
    "project_id": "metube-8bcb6",
    "storage_bucket": "metube-8bcb6.firebasestorage.app"
  },
  "client": [
    {
      "client_info": {
        "mobilesdk_app_id": "1:141070416734:android:faa7ad8036199b57da6dcf",
        "android_client_info": {
          "package_name": "com.MeTube.Live"
        }
      },
      "oauth_client": [
        {
          "client_id": "141070416734-04tt9gujrphdn9pbc4gl2brgcdkl0ruq.apps.googleusercontent.com",
          "client_type": 1,
          "android_info": {
            "package_name": "com.MeTube.Live",
            "certificate_hash": "7d2b1e4cfb37061f4a157776b6173f50270c7526"
          }
        },
        {
          "client_id": "141070416734-11gpib4ha6eeua457k5h7f48qj15lcp9.apps.googleusercontent.com",
          "client_type": 1,
          "android_info": {
            "package_name": "com.MeTube.Live",
            "certificate_hash": "ae78741b96bc412c018c2398a45c6fceb6f89616"
          }
        },
        {
          "client_id": "141070416734-26is5psq9ovhi92ig23mn6h52m26hqdu.apps.googleusercontent.com",
          "client_type": 1,
          "android_info": {
            "package_name": "com.MeTube.Live",
            "certificate_hash": "d2b4be5182bb7d0e840ab1e14d20a374f3406f72"
          }
        },
        {
          "client_id": "141070416734-4peq0ah7ko08l68kqmc5vs9tdiftkvof.apps.googleusercontent.com",
          "client_type": 1,
          "android_info": {
            "package_name": "com.MeTube.Live",
            "certificate_hash": "e64eb2db8decac14eb76afc5b201634b43c2c5cd"
          }
        },
        {
          "client_id": "141070416734-5pib4glljmong8av65f73qa8ebjru870.apps.googleusercontent.com",
          "client_type": 1,
          "android_info": {
            "package_name": "com.MeTube.Live",
            "certificate_hash": "b06949a038a27919bcae9b0db47b59111b14d0ec"
          }
        },
        {
          "client_id": "141070416734-5qmop3kp1u72nkm7hnubad8oqjlb50mn.apps.googleusercontent.com",
          "client_type": 1,
          "android_info": {
            "package_name": "com.MeTube.Live",
            "certificate_hash": "66e21b469b6e9276b16b99ec4d1b31ed695dad52"
          }
        },
        {
          "client_id": "141070416734-8jhlvg5ocgl4tq7kj6o3rrpkei97e81s.apps.googleusercontent.com",
          "client_type": 1,
          "android_info": {
            "package_name": "com.MeTube.Live",
            "certificate_hash": "a7207b6634e54e897846e1d705f530b7100c2a42"
          }
        },
        {
          "client_id": "141070416734-bc658e4p0v0l9jj1gqig25n51npc8gsl.apps.googleusercontent.com",
          "client_type": 1,
          "android_info": {
            "package_name": "com.MeTube.Live",
            "certificate_hash": "97c198100bb27e82a1c25c009772058043f339f2"
          }
        },
        {
          "client_id": "141070416734-lsmc2cm7nacv063bsr0see27sa1noae5.apps.googleusercontent.com",
          "client_type": 1,
          "android_info": {
            "package_name": "com.MeTube.Live",
            "certificate_hash": "bf900636e6273ec7be6d3f008be56d3bdabbef7a"
          }
        },
        {
          "client_id": "141070416734-ntbbjb54v6a2icu037d45ndbnep5ihkj.apps.googleusercontent.com",
          "client_type": 1,
          "android_info": {
            "package_name": "com.MeTube.Live",
            "certificate_hash": "b5a71f98f5215a3a72835e2c6e5d406bcae1d9cd"
          }
        },
        {
          "client_id": "141070416734-piquncufcnhmjg63smqbl4c2g8830kq1.apps.googleusercontent.com",
          "client_type": 1,
          "android_info": {
            "package_name": "com.MeTube.Live",
            "certificate_hash": "59c4d2aea8b1b1104267c65350f3a7a93d20d26b"
          }
        },
        {
          "client_id": "141070416734-sacenisosbmdh3qct8cben45h0tsl14u.apps.googleusercontent.com",
          "client_type": 1,
          "android_info": {
            "package_name": "com.MeTube.Live",
            "certificate_hash": "568deae4899660e08e176748e31737a4ef51ee99"
          }
        },
        {
          "client_id": "141070416734-snbsu9avs80k9dg8bap470i89206cqp9.apps.googleusercontent.com",
          "client_type": 1,
          "android_info": {
            "package_name": "com.MeTube.Live",
            "certificate_hash": "56975946097ad8ac71b1ab844f788698e3cae53b"
          }
        },
        {
          "client_id": "141070416734-v2sh8sgq99r4gcpm7umji8ddf0g4oc9p.apps.googleusercontent.com",
          "client_type": 1,
          "android_info": {
            "package_name": "com.MeTube.Live",
            "certificate_hash": "3c1a1daebe41c20622eb6de28f0a4f1fa3aa8159"
          }
        },
        {
          "client_id": "141070416734-inavs17ekr8qnkt7od2vcc8ojm8odnf6.apps.googleusercontent.com",
          "client_type": 3
        }
      ],
      "api_key": [
        {
          "current_key": "AIzaSyBVdDxVmHiRuGTGeacxzc2ASuwLYG3whUU"
        },
        {
          "current_key": "AIzaSyBtom_br8Vi5-ufIqwLnYOGGPTMnfA1nOY"
        }
      ],
      "services": {
        "appinvite_service": {
          "other_platform_oauth_client": [
            {
              "client_id": "141070416734-inavs17ekr8qnkt7od2vcc8ojm8odnf6.apps.googleusercontent.com",
              "client_type": 3
            },
            {
              "client_id": "141070416734-uu1enmi7ifmavld6ij2sbg0b9dai7hg9.apps.googleusercontent.com",
              "client_type": 2,
              "ios_info": {
                "bundle_id": "com.live.metube"
              }
            }
          ]
        }
      }
    },
    {
      "client_info": {
        "mobilesdk_app_id": "1:141070416734:android:a46087bbaff2846bda6dcf",
        "android_client_info": {
          "package_name": "com.MeTube.Live1"
        }
      },
      "oauth_client": [
        {
          "client_id": "141070416734-2soao5mdnn6e608184k16m9t5pl2kb5g.apps.googleusercontent.com",
          "client_type": 1,
          "android_info": {
            "package_name": "com.MeTube.Live1",
            "certificate_hash": "66e21b469b6e9276b16b99ec4d1b31ed695dad52"
          }
        },
        {
          "client_id": "141070416734-42b2a01h2ctun207bgiprs36opg6pm63.apps.googleusercontent.com",
          "client_type": 1,
          "android_info": {
            "package_name": "com.MeTube.Live1",
            "certificate_hash": "d2b4be5182bb7d0e840ab1e14d20a374f3406f72"
          }
        },
        {
          "client_id": "141070416734-49c0tk2agfmbtc915pgl3u1fei15idov.apps.googleusercontent.com",
          "client_type": 1,
          "android_info": {
            "package_name": "com.MeTube.Live1",
            "certificate_hash": "ae78741b96bc412c018c2398a45c6fceb6f89616"
          }
        },
        {
          "client_id": "141070416734-538nhi7onp0f1rdku8kduavlr6dst4bi.apps.googleusercontent.com",
          "client_type": 1,
          "android_info": {
            "package_name": "com.MeTube.Live1",
            "certificate_hash": "bf900636e6273ec7be6d3f008be56d3bdabbef7a"
          }
        },
        {
          "client_id": "141070416734-5p60gep8a2qqjkflptce8adn0586huln.apps.googleusercontent.com",
          "client_type": 1,
          "android_info": {
            "package_name": "com.MeTube.Live1",
            "certificate_hash": "56975946097ad8ac71b1ab844f788698e3cae53b"
          }
        },
        {
          "client_id": "141070416734-bm1gtn7rt4qamj9csjqcg5ng5j4636qr.apps.googleusercontent.com",
          "client_type": 1,
          "android_info": {
            "package_name": "com.MeTube.Live1",
            "certificate_hash": "5acbd158c2f7f6daa55c62290b66c48b558d2c88"
          }
        },
        {
          "client_id": "141070416734-klb644rfre3gck1al3iipjotgcae5ubi.apps.googleusercontent.com",
          "client_type": 1,
          "android_info": {
            "package_name": "com.MeTube.Live1",
            "certificate_hash": "07369deafa0d75a5f3f8691cec08d1a68ef26f97"
          }
        },
        {
          "client_id": "141070416734-m9iju5m0ilfhhjs29etkf94gkos47e25.apps.googleusercontent.com",
          "client_type": 1,
          "android_info": {
            "package_name": "com.MeTube.Live1",
            "certificate_hash": "e64eb2db8decac14eb76afc5b201634b43c2c5cd"
          }
        },
        {
          "client_id": "141070416734-ngofdldrk3coag848llbpcac24vdjbg1.apps.googleusercontent.com",
          "client_type": 1,
          "android_info": {
            "package_name": "com.MeTube.Live1",
            "certificate_hash": "b5a71f98f5215a3a72835e2c6e5d406bcae1d9cd"
          }
        },
        {
          "client_id": "141070416734-osa8d3flio1k2ol4utve4ar3th9d3gt2.apps.googleusercontent.com",
          "client_type": 1,
          "android_info": {
            "package_name": "com.MeTube.Live1",
            "certificate_hash": "7d2b1e4cfb37061f4a157776b6173f50270c7526"
          }
        },
        {
          "client_id": "141070416734-v772igigh3hlc2pdgqffkjtcncjf6o4j.apps.googleusercontent.com",
          "client_type": 1,
          "android_info": {
            "package_name": "com.MeTube.Live1",
            "certificate_hash": "3c1a1daebe41c20622eb6de28f0a4f1fa3aa8159"
          }
        },
        {
          "client_id": "141070416734-inavs17ekr8qnkt7od2vcc8ojm8odnf6.apps.googleusercontent.com",
          "client_type": 3
        }
      ],
      "api_key": [
        {
          "current_key": "AIzaSyBVdDxVmHiRuGTGeacxzc2ASuwLYG3whUU"
        },
        {
          "current_key": "AIzaSyBtom_br8Vi5-ufIqwLnYOGGPTMnfA1nOY"
        }
      ],
      "services": {
        "appinvite_service": {
          "other_platform_oauth_client": [
            {
              "client_id": "141070416734-inavs17ekr8qnkt7od2vcc8ojm8odnf6.apps.googleusercontent.com",
              "client_type": 3
            },
            {
              "client_id": "141070416734-uu1enmi7ifmavld6ij2sbg0b9dai7hg9.apps.googleusercontent.com",
              "client_type": 2,
              "ios_info": {
                "bundle_id": "com.live.metube"
              }
            }
          ]
        }
      }
    },
    {
      "client_info": {
        "mobilesdk_app_id": "1:141070416734:android:47af463f632839cada6dcf",
        "android_client_info": {
          "package_name": "com.testMe"
        }
      },
      "oauth_client": [
        {
          "client_id": "141070416734-ctjehc910mrqsalhanasfa6njhn99nlv.apps.googleusercontent.com",
          "client_type": 1,
          "android_info": {
            "package_name": "com.testMe",
            "certificate_hash": "3c1a1daebe41c20622eb6de28f0a4f1fa3aa8159"
          }
        },
        {
          "client_id": "141070416734-iljfkovesghoa4e83e40okdl3bjmh5d7.apps.googleusercontent.com",
          "client_type": 1,
          "android_info": {
            "package_name": "com.testMe",
            "certificate_hash": "e64eb2db8decac14eb76afc5b201634b43c2c5cd"
          }
        },
        {
          "client_id": "141070416734-vj5oojftc478k5tnnestgk7ld3hv3v8r.apps.googleusercontent.com",
          "client_type": 1,
          "android_info": {
            "package_name": "com.testMe",
            "certificate_hash": "d2b4be5182bb7d0e840ab1e14d20a374f3406f72"
          }
        },
        {
          "client_id": "141070416734-inavs17ekr8qnkt7od2vcc8ojm8odnf6.apps.googleusercontent.com",
          "client_type": 3
        }
      ],
      "api_key": [
        {
          "current_key": "AIzaSyBVdDxVmHiRuGTGeacxzc2ASuwLYG3whUU"
        },
        {
          "current_key": "AIzaSyBtom_br8Vi5-ufIqwLnYOGGPTMnfA1nOY"
        }
      ],
      "services": {
        "appinvite_service": {
          "other_platform_oauth_client": [
            {
              "client_id": "141070416734-inavs17ekr8qnkt7od2vcc8ojm8odnf6.apps.googleusercontent.com",
              "client_type": 3
            },
            {
              "client_id": "141070416734-uu1enmi7ifmavld6ij2sbg0b9dai7hg9.apps.googleusercontent.com",
              "client_type": 2,
              "ios_info": {
                "bundle_id": "com.live.metube"
              }
            }
          ]
        }
      }
    }
  ],
  "configuration_version": "1"
}